mimic/__init__.py
mimic/catalog.py
mimic/core.py
mimic/imimic.py
mimic/resource.py
mimic/session.py
mimic/tap.py
mimic/canned_responses/__init__.py
mimic/canned_responses/auth.py
mimic/canned_responses/fastly.py
mimic/canned_responses/glance.py
mimic/canned_responses/loadbalancer.py
mimic/canned_responses/maas_alarm_examples.py
mimic/canned_responses/maas_json_home.py
mimic/canned_responses/maas_monitoring_zones.py
mimic/canned_responses/mimic_presets.py
mimic/canned_responses/noit.py
mimic/canned_responses/noit_metrics_fixture.py
mimic/canned_responses/nova.py
mimic/canned_responses/json/__init__.py
mimic/canned_responses/json/glance/__init__.py
mimic/canned_responses/json/glance/glance_images_json.py
mimic/model/__init__.py
mimic/model/behaviors.py
mimic/model/clb_errors.py
mimic/model/clb_objects.py
mimic/model/cloudfeeds.py
mimic/model/customer_objects.py
mimic/model/flavor_collections.py
mimic/model/flavors.py
mimic/model/glance_objects.py
mimic/model/heat_objects.py
mimic/model/identity.py
mimic/model/identity_errors.py
mimic/model/identity_objects.py
mimic/model/ironic_objects.py
mimic/model/keypair_objects.py
mimic/model/maas_errors.py
mimic/model/maas_objects.py
mimic/model/mailgun_objects.py
mimic/model/nova_image_collection.py
mimic/model/nova_objects.py
mimic/model/queue_objects.py
mimic/model/rackspace_image_store.py
mimic/model/rackspace_images.py
mimic/model/valkyrie_objects.py
mimic/model/yo_objects.py
mimic/plugins/__init__.py
mimic/plugins/cinder_plugin.py
mimic/plugins/cloudfeeds_plugin.py
mimic/plugins/dns_plugin.py
mimic/plugins/glance_plugin.py
mimic/plugins/heat_plugin.py
mimic/plugins/loadbalancer_plugin.py
mimic/plugins/maas_plugin.py
mimic/plugins/neutron_plugin.py
mimic/plugins/nova_plugin.py
mimic/plugins/queue_plugin.py
mimic/plugins/rackconnect_v3_plugin.py
mimic/plugins/swift_plugin.py
mimic/plugins/yo_plugin.py
mimic/rest/__init__.py
mimic/rest/cinder_api.py
mimic-2.2.0.dist-info/DESCRIPTION.rst
mimic-2.2.0.dist-info/METADATA
mimic-2.2.0.dist-info/RECORD
mimic-2.2.0.dist-info/WHEEL
mimic-2.2.0.dist-info/metadata.json
mimic-2.2.0.dist-info/top_level.txt
