Metadata-Version: 2.0
Name: mimic
Version: 2.2.0
Summary: An API-compatible mock service
Home-page: https://github.com/rackerlabs/mimic
Author: UNKNOWN
Author-email: UNKNOWN
License: Apache License, Version 2.0
Platform: UNKNOWN
Classifier: Environment :: Web Environment
Classifier: Intended Audience :: Developers
Classifier: Operating System :: OS Independent
Classifier: Programming Language :: Python
Classifier: Programming Language :: Python :: 2.7
Classifier: Programming Language :: Python :: 3.4
Classifier: Programming Language :: Python :: 3.5
Classifier: Programming Language :: Python :: Implementation :: CPython
Classifier: Programming Language :: Python :: Implementation :: PyPy
Classifier: Topic :: Internet :: WWW/HTTP :: Dynamic Content
Classifier: Topic :: Software Development :: Libraries :: Python Modules
Requires-Dist: klein (>=15.3.1)
Requires-Dist: twisted (>=15.5.0)
Requires-Dist: treq (>=15.1.0)
Requires-Dist: six (>=1.6.0)
Requires-Dist: xmltodict (>=0.9.1)
Requires-Dist: attrs (>=15.1.0)
Requires-Dist: testtools (<1.8.0,>=1.7.1)
Requires-Dist: iso8601 (>=0.1.10)
